MSUtils/ClassESW.py
MSUtils/__init__.py
MSUtils/flag_stats.py
MSUtils/imp_plotter.py
MSUtils/msutils.py
msutils-1.2.0.dist-info/LICENSE
msutils-1.2.0.dist-info/METADATA
msutils-1.2.0.dist-info/WHEEL
msutils-1.2.0.dist-info/top_level.txt
msutils-1.2.0.dist-info/RECORD
