Metadata-Version: 2.1
Name: msutils
Version: 1.2.0
Summary: Tools for playing with Measurement sets.
Home-page: https://github.com/SpheMakh/msutils
Author: Sphesihle Makhathini
Author-email: sphemakh@gmail.com
License: GNU GPL v2
Platform: UNKNOWN
Classifier: Development Status :: 3 - Alpha
Classifier: Intended Audience :: Developers
Classifier: Operating System :: OS Independent
Classifier: Programming Language :: Python
Classifier: Topic :: Software Development :: Libraries :: Python Modules
Classifier: Topic :: Scientific/Engineering :: Astronomy
Requires-Python: >=3.6
Requires-Dist: numpy
Requires-Dist: scipy
Requires-Dist: matplotlib
Requires-Dist: dask-ms
Requires-Dist: bokeh
